wellshuffled/__init__.py
wellshuffled/cli.py
wellshuffled/plate_generator.py
wellshuffled/utilities.py
wellshuffled-0.1.0.dist-info/METADATA
wellshuffled-0.1.0.dist-info/WHEEL
wellshuffled-0.1.0.dist-info/entry_points.txt
wellshuffled-0.1.0.dist-info/licenses/LICENSE
wellshuffled-0.1.0.dist-info/RECORD
