Metadata-Version: 2.4
Name: wellshuffled
Version: 0.1.0
Summary: A command line utility for shuffling biological sample positions in microwell plates.
Project-URL: Homepage, https://github.com/exfab/wellshuffled
Project-URL: Repository, https://github.com/exfab/wellshuffled.git
Project-URL: Issues, https://github.com/exfab/wellshuffled/issues
Author-email: Andrew McNaughton <mcnaughtonadm@gmail.com>
Maintainer-email: Andrew McNaughton <mcnaughtonadm@gmail.com>
License: MIT License
License-File: LICENSE
Keywords: microwell plate,plate randomization
Classifier: Development Status :: 3 - Alpha
Classifier: License :: OSI Approved :: MIT License
Classifier: Programming Language :: Python :: 3.11
Requires-Python: >=3.11
Requires-Dist: click>=8.3.0
Requires-Dist: numpy>=2.3.3
